oscarbundles/__init__.py
oscarbundles/admin.py
oscarbundles/apps.py
oscarbundles/models.py
oscarbundles/py.typed
oscarbundles/api/__init__.py
oscarbundles/api/apps.py
oscarbundles/api/serializers.py
oscarbundles/api/views.py
oscarbundles/dashboard/__init__.py
oscarbundles/dashboard/apps.py
oscarbundles/dashboard/views.py
oscarbundles/fixtures/bundles-test.yaml
oscarbundles/locale/es/LC_MESSAGES/django.mo
oscarbundles/locale/es/LC_MESSAGES/django.po
oscarbundles/locale/es/LC_MESSAGES/djangojs.mo
oscarbundles/locale/es/LC_MESSAGES/djangojs.po
oscarbundles/migrations/0001_initial.py
oscarbundles/migrations/0001_squashed_0016_auto_20190906_1645.py
oscarbundles/migrations/0002_auto_20160902_1106.py
oscarbundles/migrations/0002_bundlegroup_is_active.py
oscarbundles/migrations/0003_alter_bundlegroup_is_active.py
oscarbundles/migrations/0003_auto_20180315_1137.py
oscarbundles/migrations/0004_auto_20180315_1349.py
oscarbundles/migrations/0005_bundleentry.py
oscarbundles/migrations/0006_auto_20180318_1907.py
oscarbundles/migrations/0007_auto_20180318_1919.py
oscarbundles/migrations/0008_auto_20180318_1933.py
oscarbundles/migrations/0009_auto_20180319_1116.py
oscarbundles/migrations/0010_auto_20180319_1116.py
oscarbundles/migrations/0011_auto_20180319_1121.py
oscarbundles/migrations/0012_auto_20180319_1613.py
oscarbundles/migrations/0013_bundlegroup_headline.py
oscarbundles/migrations/0014_auto_20190305_0420.py
oscarbundles/migrations/0015_auto_20190826_1326.py
oscarbundles/migrations/0016_auto_20190906_1645.py
oscarbundles/migrations/__init__.py
oscarbundles/static/oscarbundles/bundles.css
oscarbundles/static/oscarbundles/bundles.css.map
oscarbundles/static/oscarbundles/bundles.js
oscarbundles/static/oscarbundles/bundles.js.map
oscarbundles/static/oscarbundles/vendor.js
oscarbundles/static/oscarbundles/vendor.js.LICENSE.txt
oscarbundles/static/oscarbundles/vendor.js.map
oscarbundles/static/oscarbundles/webpack-stats.json
django_oscar_bundles-2.4.0.dist-info/METADATA
django_oscar_bundles-2.4.0.dist-info/WHEEL
django_oscar_bundles-2.4.0.dist-info/RECORD
