Metadata-Version: 2.4
Name: django-oscar-bundles
Version: 2.4.0
Summary: An extension on top of django-oscar providing product bundle functionality.
Project-URL: Homepage, https://gitlab.com/thelabnyc/django-oscar/django-oscar-bundles/
Project-URL: Repository, https://gitlab.com/thelabnyc/django-oscar/django-oscar-bundles/
Author-email: thelab <thelabdev@thelab.co>
License: ISC
Requires-Python: >=3.12
Requires-Dist: django-oscar-api==3.3.0
Requires-Dist: django-oscar<4.1,>=4.0
Requires-Dist: django-stubs-ext<6,>=5.1.3
Requires-Dist: django>=4.2
Requires-Dist: phonenumbers<10,>=9.0.3
